Workbook

Sheet Instrucoes
B1: M3sec — Planilha Operacional de Triagem
B2: Versao 1.0 — agosto/2026
B4: LEGENDA DE CORES
B5: Texto AZUL | C5: Celula de preenchimento manual. Voce edita.
B6: Texto PRETO | C6: Formula. Nao editar — o valor e calculado.
B7: Fundo AMARELO | C7: Premissa comercial. Revisar antes de usar em producao.
B9: ABAS
B10: Parametros | C10: Precos, SLA e percentual de exito esperado por faixa. Comece por aqui.
B11: Catalogo | C11: Tipos de conteudo com faixa, fundamento juridico e camada de ataque. Base de todo o resto.
B12: Triagem | C12: Aba de trabalho diario. Uma linha por ITEM (uma URL). Preencha as colunas azuis.
B13: Casos | C13: Consolidacao por caso: contagem de itens por faixa, receita e taxa de exito.
B14: Painel | C14: Indicadores gerais. Somente leitura.
B16: COMO USAR — PASSO A PASSO
B17: 1. Diagnostico | C17: Para cada URL encontrada na varredura, crie uma linha na aba Triagem.
B18: 2. Classificar | C18: Selecione o Tipo de conteudo na lista suspensa. Faixa, fundamento, camada, prazo e preco sao preenchidos automaticamente.
B19: 3. Faixa D | C19: Aparece no relatorio do cliente como NAO EXECUTAVEL e com valor zero. Nunca cobrar.
B20: 4. Executar | C20: Atualize o Status a cada movimentacao. Ordem obrigatoria: Fonte > Plataforma > Indexador.
B21: 5. Verificar | C21: So marque VERIFICADO apos confirmar em busca anonima. So ha faturamento de exito apos verificacao.
B22: 6. Calibrar | C22: A cada 20 casos, compare o exito real com o esperado. Divergencia acima de 20% exige reclassificar o tipo no Catalogo.
B24: REGRA INEGOCIAVEL
C25: Item de Faixa D nunca e cobrado e nunca e executado. O relatorio que recusa cobrar e a principal peca de conversao comercial da M3sec.
B27: AVISO
C28: Os fundamentos juridicos sao referencias de trabalho, nao parecer. Validar com o advogado parceiro antes do primeiro caso.
C29: Os precos sao premissas iniciais, nao cotacao. Recalibrar com dados reais apos os 10 primeiros casos.

Sheet Parametros
B1: PARAMETROS COMERCIAIS
B2: Celulas azuis com fundo amarelo sao premissas. Ajuste antes de usar.
B4: Valores fixos
B5: Item | C5: Valor (R$) | F5: Observacao
B6: Diagnostico (por caso) | C6: 197 | F6: Sempre cobrado. Filtra curioso e cobre o custo da varredura.
B7: Execucao Faixa B (por item) | C7: 300 | F7: Cobre o custo de certidoes e horas em caso de exito incerto.
B8: Monitoramento PF (mensal) | C8: 79 | F8: Receita recorrente. Metrica que define a sustentabilidade do negocio.
B9: Monitoramento PJ (mensal) | C9: 590 | F9: Empresas, executivos e escritorios parceiros.
B11: Tabela por faixa
B12: Faixa | C12: Exito esperado | D12: Preco de exito (R$) | E12: SLA (dias) | F12: Regra comercial
B13: A | C13: 0.875 | D13: 650 | E13: 30 | F13: Aceitar. Prazo prometido. Prioridade de execucao.
B14: B | C14: 0.6 | D14: 1400 | E14: 60 | F14: Aceitar com prognostico escrito. Exito parcial e resultado valido.
B15: C | C15: 0.275 | D15: 1500 | E15: 90 | F15: Somente com termo de ciencia. Sem promessa. Cobranca so por exito.
B16: D | C16: 0.05 | D16: 0 | E16: 0 | F16: RECUSAR. Sem cobranca, sem execucao.
B19: Fonte dos valores: premissas definidas pelo usuario em agosto/2026. Nenhum valor deriva de cotacao de mercado.

Sheet Catalogo
A1: ID | B1: Tipo de conteudo | C1: Faixa | D1: Fundamento | E1: Camada prioritaria | F1: Prazo tipico | G1: Condicao / observacao
A2: T01 | B2: Processo em segredo de justica indevidamente indexado | C2: A | D2: CPC art. 189 | E2: Fonte (Tribunal) | F2: 5-20 dias | G2: Confirmar decreto de sigilo. Erro de classificacao na origem.
A3: T02 | B3: Dados de crianca ou adolescente | C3: A | D3: ECA arts. 17 e 143; LGPD art. 14 | E3: Plataforma | F3: 2-10 dias | G3: Prioridade maxima. Plataformas removem de imediato apos notificacao.
A4: T03 | B4: Acao de familia (divorcio, alimentos, guarda, paternidade) | C4: A | D4: CPC art. 189, II | E4: Fonte (Tribunal) | F4: 10-30 dias | G4: Segredo por natureza. Pedir correcao de classificacao no tribunal.
A5: T04 | B5: Dados sensiveis (saude, interdicao, orientacao sexual, religiao) | C5: A | D5: LGPD arts. 5o II e 11 | E5: Plataforma | F5: 10-30 dias | G5: Identificar o dado sensivel especifico no pedido.
A6: T05 | B6: Conteudo intimo nao consensual | C6: A | D6: Marco Civil art. 21; Lei 13.718/2018 | E6: Hospedeiro | F6: 1-7 dias | G6: Remocao independe de ordem judicial. Tratar como urgencia.
A7: T06 | B7: Dados de contato (endereco, telefone, e-mail, CPF, RG) | C7: A | D7: LGPD art. 18 | E7: Indexador (Google) | F7: 3-15 dias | G7: Ferramenta propria do Google. Cliente conclui com a propria identidade.
A8: T07 | B8: Homonimo - processo de terceiro atribuido ao cliente | C8: A | D8: LGPD art. 18, III | E8: Plataforma | F8: 5-15 dias | G8: Anexar prova de que o CPF nao corresponde.
A9: T08 | B9: Processo excluido na fonte, ainda em cache ou indice | C9: A | D9: LGPD art. 18, IV | E9: Indexador (Google) | F9: 3-10 dias | G9: Comprovar que a URL de origem ja nao existe.
A10: T09 | B10: Criminal com absolvicao transitada em julgado | C10: B | D10: CP art. 93; desindexacao | E10: Fonte (Tribunal) | F10: 30-60 dias | G10: Exige certidao de transito em julgado. Sem ela, reclassificar para C.
A11: T10 | B11: Inquerito arquivado sem denuncia | C11: B | D11: Ausencia de acusacao formal; LGPD art. 18 | E11: Plataforma | F11: 20-45 dias | G11: Argumento forte: nao houve processo. Anexar certidao de arquivamento.
A12: T11 | B12: Pena cumprida ou extinta ha mais de 2 anos | C12: B | D12: LEP art. 202 | E12: Fonte (Tribunal) | F12: 30-60 dias | G12: Fundamento subutilizado pelo mercado. Explorar.
... A29: T28 | B29: Pedido de terceiro sobre dados alheios | C29: D | D29: Ilegal e tecnicamente inviavel | E29: RECUSAR | F29: - | G29: Verificacao de identidade das plataformas bloqueia.

Sheet Triagem
A1: Item ID | B1: Caso ID | C1: Cliente | D1: URL do item | E1: Tipo de conteudo | F1: Faixa | G1: Fundamento | H1: Camada prioritaria | I1: Exito esperado | J1: SLA (dias) | K1: Data de entrada | L1: Prazo limite | M1: Status | N1: Data protocolo | O1: Data verificacao | P1: Preco de exito | Q1: Faturavel | R1: A faturar
A2: IT001 | B2: C001 | C2: Exemplo - Joao Silva | D2: https://www.escavador.com/processos/exemplo-1 | E2: Inquerito arquivado sem denuncia | F2: =IFERROR(INDEX(Catalogo!$C$2:$C$29,MATCH($E2,Catalogo!$B$2:$B$29,0)),"") -> B | G2: =IFERROR(INDEX(Catalogo!$D$2:$D$29,MATCH($E2,Catalogo!$B$2:$B$29,0)),"") -> Ausencia de acusacao formal; LGPD art. 18 | H2: =IFERROR(INDEX(Catalogo!$E$2:$E$29,MATCH($E2,Catalogo!$B$2:$B$29,0)),"") -> Plataforma | I2: =IFERROR(INDEX(Parametros!$C$13:$C$16,MATCH($F2,Parametros!$B$13:$B$16,0)),"") -> 0.6 | J2: =IFERROR(INDEX(Parametros!$E$13:$E$16,MATCH($F2,Parametros!$B$13:$B$16,0)),"") -> 60 | K2: 2026-08-05 | L2: =IF(OR($K2="",$J2="",$J2=0),"",$K2+$J2) -> 46299 | M2: PROTOCOLADO | N2: 2026-08-06 | P2: =IFERROR(INDEX(Parametros!$D$13:$D$16,MATCH($F2,Parametros!$B$13:$B$16,0)),"") -> 1400 | Q2: =IF($F2="","",IF($F2="D","NAO","SIM")) -> SIM | R2: =IF(AND($M2="VERIFICADO",$Q2="SIM"),$P2,0) -> 0
A3: IT002 | B3: C001 | C3: Exemplo - Joao Silva | D3: https://www.jusbrasil.com.br/processos/exemplo-2 | E3: Dados de contato (endereco, telefone, e-mail, CPF, RG) | F3: =IFERROR(INDEX(Catalogo!$C$2:$C$29,MATCH($E3,Catalogo!$B$2:$B$29,0)),"") -> A | G3: =IFERROR(INDEX(Catalogo!$D$2:$D$29,MATCH($E3,Catalogo!$B$2:$B$29,0)),"") -> LGPD art. 18 | H3: =IFERROR(INDEX(Catalogo!$E$2:$E$29,MATCH($E3,Catalogo!$B$2:$B$29,0)),"") -> Indexador (Google) | I3: =IFERROR(INDEX(Parametros!$C$13:$C$16,MATCH($F3,Parametros!$B$13:$B$16,0)),"") -> 0.875 | J3: =IFERROR(INDEX(Parametros!$E$13:$E$16,MATCH($F3,Parametros!$B$13:$B$16,0)),"") -> 30 | K3: 2026-08-05 | L3: =IF(OR($K3="",$J3="",$J3=0),"",$K3+$J3) -> 46269 | M3: VERIFICADO | N3: 2026-08-06 | O3: 2026-08-14 | P3: =IFERROR(INDEX(Parametros!$D$13:$D$16,MATCH($F3,Parametros!$B$13:$B$16,0)),"") -> 650 | Q3: =IF($F3="","",IF($F3="D","NAO","SIM")) -> SIM | R3: =IF(AND($M3="VERIFICADO",$Q3="SIM"),$P3,0) -> 650
A4: IT003 | B4: C001 | C4: Exemplo - Joao Silva | D4: https://noticias.exemplo.com.br/materia-exemplo | E4: Materia jornalistica verdadeira e licitamente publicada | F4: =IFERROR(INDEX(Catalogo!$C$2:$C$29,MATCH($E4,Catalogo!$B$2:$B$29,0)),"") -> D | G4: =IFERROR(INDEX(Catalogo!$D$2:$D$29,MATCH($E4,Catalogo!$B$2:$B$29,0)),"") -> STF Tema 786 - RE 1.010.606 | H4: =IFERROR(INDEX(Catalogo!$E$2:$E$29,MATCH($E4,Catalogo!$B$2:$B$29,0)),"") -> RECUSAR | I4: =IFERROR(INDEX(Parametros!$C$13:$C$16,MATCH($F4,Parametros!$B$13:$B$16,0)),"") -> 0.05 | J4: =IFERROR(INDEX(Parametros!$E$13:$E$16,MATCH($F4,Parametros!$B$13:$B$16,0)),"") -> 0 | K4: 2026-08-05 | L4: =IF(OR($K4="",$J4="",$J4=0),"",$K4+$J4) | M4: RECUSADO | P4: =IFERROR(INDEX(Parametros!$D$13:$D$16,MATCH($F4,Parametros!$B$13:$B$16,0)),"") -> 0 | Q4: =IF($F4="","",IF($F4="D","NAO","SIM")) -> NAO | R4: =IF(AND($M4="VERIFICADO",$Q4="SIM"),$P4,0) -> 0
F5: =IFERROR(INDEX(Catalogo!$C$2:$C$29,MATCH($E5,Catalogo!$B$2:$B$29,0)),"") | G5: =IFERROR(INDEX(Catalogo!$D$2:$D$29,MATCH($E5,Catalogo!$B$2:$B$29,0)),"") | H5: =IFERROR(INDEX(Catalogo!$E$2:$E$29,MATCH($E5,Catalogo!$B$2:$B$29,0)),"") | I5: =IFERROR(INDEX(Parametros!$C$13:$C$16,MATCH($F5,Parametros!$B$13:$B$16,0)),"") | J5: =IFERROR(INDEX(Parametros!$E$13:$E$16,MATCH($F5,Parametros!$B$13:$B$16,0)),"") | L5: =IF(OR($K5="",$J5="",$J5=0),"",$K5+$J5) | P5: =IFERROR(INDEX(Parametros!$D$13:$D$16,MATCH($F5,Parametros!$B$13:$B$16,0)),"") | Q5: =IF($F5="","",IF($F5="D","NAO","SIM")) | R5: =IF(AND($M5="VERIFICADO",$Q5="SIM"),$P5,0) -> 0
F6: =IFERROR(INDEX(Catalogo!$C$2:$C$29,MATCH($E6,Catalogo!$B$2:$B$29,0)),"") | G6: =IFERROR(INDEX(Catalogo!$D$2:$D$29,MATCH($E6,Catalogo!$B$2:$B$29,0)),"") | H6: =IFERROR(INDEX(Catalogo!$E$2:$E$29,MATCH($E6,Catalogo!$B$2:$B$29,0)),"") | I6: =IFERROR(INDEX(Parametros!$C$13:$C$16,MATCH($F6,Parametros!$B$13:$B$16,0)),"") | J6: =IFERROR(INDEX(Parametros!$E$13:$E$16,MATCH($F6,Parametros!$B$13:$B$16,0)),"") | L6: =IF(OR($K6="",$J6="",$J6=0),"",$K6+$J6) | P6: =IFERROR(INDEX(Parametros!$D$13:$D$16,MATCH($F6,Parametros!$B$13:$B$16,0)),"") | Q6: =IF($F6="","",IF($F6="D","NAO","SIM")) | R6: =IF(AND($M6="VERIFICADO",$Q6="SIM"),$P6,0) -> 0
F7: =IFERROR(INDEX(Catalogo!$C$2:$C$29,MATCH($E7,Catalogo!$B$2:$B$29,0)),"") | G7: =IFERROR(INDEX(Catalogo!$D$2:$D$29,MATCH($E7,Catalogo!$B$2:$B$29,0)),"") | H7: =IFERROR(INDEX(Catalogo!$E$2:$E$29,MATCH($E7,Catalogo!$B$2:$B$29,0)),"") | I7: =IFERROR(INDEX(Parametros!$C$13:$C$16,MATCH($F7,Parametros!$B$13:$B$16,0)),"") | J7: =IFERROR(INDEX(Parametros!$E$13:$E$16,MATCH($F7,Parametros!$B$13:$B$16,0)),"") | L7: =IF(OR($K7="",$J7="",$J7=0),"",$K7+$J7) | P7: =IFERROR(INDEX(Parametros!$D$13:$D$16,MATCH($F7,Parametros!$B$13:$B$16,0)),"") | Q7: =IF($F7="","",IF($F7="D","NAO","SIM")) | R7: =IF(AND($M7="VERIFICADO",$Q7="SIM"),$P7,0) -> 0
F8: =IFERROR(INDEX(Catalogo!$C$2:$C$29,MATCH($E8,Catalogo!$B$2:$B$29,0)),"") | G8: =IFERROR(INDEX(Catalogo!$D$2:$D$29,MATCH($E8,Catalogo!$B$2:$B$29,0)),"") | H8: =IFERROR(INDEX(Catalogo!$E$2:$E$29,MATCH($E8,Catalogo!$B$2:$B$29,0)),"") | I8: =IFERROR(INDEX(Parametros!$C$13:$C$16,MATCH($F8,Parametros!$B$13:$B$16,0)),"") | J8: =IFERROR(INDEX(Parametros!$E$13:$E$16,MATCH($F8,Parametros!$B$13:$B$16,0)),"") | L8: =IF(OR($K8="",$J8="",$J8=0),"",$K8+$J8) | P8: =IFERROR(INDEX(Parametros!$D$13:$D$16,MATCH($F8,Parametros!$B$13:$B$16,0)),"") | Q8: =IF($F8="","",IF($F8="D","NAO","SIM")) | R8: =IF(AND($M8="VERIFICADO",$Q8="SIM"),$P8,0) -> 0
F9: =IFERROR(INDEX(Catalogo!$C$2:$C$29,MATCH($E9,Catalogo!$B$2:$B$29,0)),"") | G9: =IFERROR(INDEX(Catalogo!$D$2:$D$29,MATCH($E9,Catalogo!$B$2:$B$29,0)),"") | H9: =IFERROR(INDEX(Catalogo!$E$2:$E$29,MATCH($E9,Catalogo!$B$2:$B$29,0)),"") | I9: =IFERROR(INDEX(Parametros!$C$13:$C$16,MATCH($F9,Parametros!$B$13:$B$16,0)),"") | J9: =IFERROR(INDEX(Parametros!$E$13:$E$16,MATCH($F9,Parametros!$B$13:$B$16,0)),"") | L9: =IF(OR($K9="",$J9="",$J9=0),"",$K9+$J9) | P9: =IFERROR(INDEX(Parametros!$D$13:$D$16,MATCH($F9,Parametros!$B$13:$B$16,0)),"") | Q9: =IF($F9="","",IF($F9="D","NAO","SIM")) | R9: =IF(AND($M9="VERIFICADO",$Q9="SIM"),$P9,0) -> 0
F10: =IFERROR(INDEX(Catalogo!$C$2:$C$29,MATCH($E10,Catalogo!$B$2:$B$29,0)),"") | G10: =IFERROR(INDEX(Catalogo!$D$2:$D$29,MATCH($E10,Catalogo!$B$2:$B$29,0)),"") | H10: =IFERROR(INDEX(Catalogo!$E$2:$E$29,MATCH($E10,Catalogo!$B$2:$B$29,0)),"") | I10: =IFERROR(INDEX(Parametros!$C$13:$C$16,MATCH($F10,Parametros!$B$13:$B$16,0)),"") | J10: =IFERROR(INDEX(Parametros!$E$13:$E$16,MATCH($F10,Parametros!$B$13:$B$16,0)),"") | L10: =IF(OR($K10="",$J10="",$J10=0),"",$K10+$J10) | P10: =IFERROR(INDEX(Parametros!$D$13:$D$16,MATCH($F10,Parametros!$B$13:$B$16,0)),"") | Q10: =IF($F10="","",IF($F10="D","NAO","SIM")) | R10: =IF(AND($M10="VERIFICADO",$Q10="SIM"),$P10,0) -> 0
F11: =IFERROR(INDEX(Catalogo!$C$2:$C$29,MATCH($E11,Catalogo!$B$2:$B$29,0)),"") | G11: =IFERROR(INDEX(Catalogo!$D$2:$D$29,MATCH($E11,Catalogo!$B$2:$B$29,0)),"") | H11: =IFERROR(INDEX(Catalogo!$E$2:$E$29,MATCH($E11,Catalogo!$B$2:$B$29,0)),"") | I11: =IFERROR(INDEX(Parametros!$C$13:$C$16,MATCH($F11,Parametros!$B$13:$B$16,0)),"") | J11: =IFERROR(INDEX(Parametros!$E$13:$E$16,MATCH($F11,Parametros!$B$13:$B$16,0)),"") | L11: =IF(OR($K11="",$J11="",$J11=0),"",$K11+$J11) | P11: =IFERROR(INDEX(Parametros!$D$13:$D$16,MATCH($F11,Parametros!$B$13:$B$16,0)),"") | Q11: =IF($F11="","",IF($F11="D","NAO","SIM")) | R11: =IF(AND($M11="VERIFICADO",$Q11="SIM"),$P11,0) -> 0
F12: =IFERROR(INDEX(Catalogo!$C$2:$C$29,MATCH($E12,Catalogo!$B$2:$B$29,0)),"") | G12: =IFERROR(INDEX(Catalogo!$D$2:$D$29,MATCH($E12,Catalogo!$B$2:$B$29,0)),"") | H12: =IFERROR(INDEX(Catalogo!$E$2:$E$29,MATCH($E12,Catalogo!$B$2:$B$29,0)),"") | I12: =IFERROR(INDEX(Parametros!$C$13:$C$16,MATCH($F12,Parametros!$B$13:$B$16,0)),"") | J12: =IFERROR(INDEX(Parametros!$E$13:$E$16,MATCH($F12,Parametros!$B$13:$B$16,0)),"") | L12: =IF(OR($K12="",$J12="",$J12=0),"",$K12+$J12) | P12: =IFERROR(INDEX(Parametros!$D$13:$D$16,MATCH($F12,Parametros!$B$13:$B$16,0)),"") | Q12: =IF($F12="","",IF($F12="D","NAO","SIM")) | R12: =IF(AND($M12="VERIFICADO",$Q12="SIM"),$P12,0) -> 0
F13: =IFERROR(INDEX(Catalogo!$C$2:$C$29,MATCH($E13,Catalogo!$B$2:$B$29,0)),"") | G13: =IFERROR(INDEX(Catalogo!$D$2:$D$29,MATCH($E13,Catalogo!$B$2:$B$29,0)),"") | H13: =IFERROR(INDEX(Catalogo!$E$2:$E$29,MATCH($E13,Catalogo!$B$2:$B$29,0)),"") | I13: =IFERROR(INDEX(Parametros!$C$13:$C$16,MATCH($F13,Parametros!$B$13:$B$16,0)),"") | J13: =IFERROR(INDEX(Parametros!$E$13:$E$16,MATCH($F13,Parametros!$B$13:$B$16,0)),"") | L13: =IF(OR($K13="",$J13="",$J13=0),"",$K13+$J13) | P13: =IFERROR(INDEX(Parametros!$D$13:$D$16,MATCH($F13,Parametros!$B$13:$B$16,0)),"") | Q13: =IF($F13="","",IF($F13="D","NAO","SIM")) | R13: =IF(AND($M13="VERIFICADO",$Q13="SIM"),$P13,0) -> 0
F14: =IFERROR(INDEX(Catalogo!$C$2:$C$29,MATCH($E14,Catalogo!$B$2:$B$29,0)),"") | G14: =IFERROR(INDEX(Catalogo!$D$2:$D$29,MATCH($E14,Catalogo!$B$2:$B$29,0)),"") | H14: =IFERROR(INDEX(Catalogo!$E$2:$E$29,MATCH($E14,Catalogo!$B$2:$B$29,0)),"") | I14: =IFERROR(INDEX(Parametros!$C$13:$C$16,MATCH($F14,Parametros!$B$13:$B$16,0)),"") | J14: =IFERROR(INDEX(Parametros!$E$13:$E$16,MATCH($F14,Parametros!$B$13:$B$16,0)),"") | L14: =IF(OR($K14="",$J14="",$J14=0),"",$K14+$J14) | P14: =IFERROR(INDEX(Parametros!$D$13:$D$16,MATCH($F14,Parametros!$B$13:$B$16,0)),"") | Q14: =IF($F14="","",IF($F14="D","NAO","SIM")) | R14: =IF(AND($M14="VERIFICADO",$Q14="SIM"),$P14,0) -> 0
F15: =IFERROR(INDEX(Catalogo!$C$2:$C$29,MATCH($E15,Catalogo!$B$2:$B$29,0)),"") | G15: =IFERROR(INDEX(Catalogo!$D$2:$D$29,MATCH($E15,Catalogo!$B$2:$B$29,0)),"") | H15: =IFERROR(INDEX(Catalogo!$E$2:$E$29,MATCH($E15,Catalogo!$B$2:$B$29,0)),"") | I15: =IFERROR(INDEX(Parametros!$C$13:$C$16,MATCH($F15,Parametros!$B$13:$B$16,0)),"") | J15: =IFERROR(INDEX(Parametros!$E$13:$E$16,MATCH($F15,Parametros!$B$13:$B$16,0)),"") | L15: =IF(OR($K15="",$J15="",$J15=0),"",$K15+$J15) | P15: =IFERROR(INDEX(Parametros!$D$13:$D$16,MATCH($F15,Parametros!$B$13:$B$16,0)),"") | Q15: =IF($F15="","",IF($F15="D","NAO","SIM")) | R15: =IF(AND($M15="VERIFICADO",$Q15="SIM"),$P15,0) -> 0
F16: =IFERROR(INDEX(Catalogo!$C$2:$C$29,MATCH($E16,Catalogo!$B$2:$B$29,0)),"") | G16: =IFERROR(INDEX(Catalogo!$D$2:$D$29,MATCH($E16,Catalogo!$B$2:$B$29,0)),"") | H16: =IFERROR(INDEX(Catalogo!$E$2:$E$29,MATCH($E16,Catalogo!$B$2:$B$29,0)),"") | I16: =IFERROR(INDEX(Parametros!$C$13:$C$16,MATCH($F16,Parametros!$B$13:$B$16,0)),"") | J16: =IFERROR(INDEX(Parametros!$E$13:$E$16,MATCH($F16,Parametros!$B$13:$B$16,0)),"") | L16: =IF(OR($K16="",$J16="",$J16=0),"",$K16+$J16) | P16: =IFERROR(INDEX(Parametros!$D$13:$D$16,MATCH($F16,Parametros!$B$13:$B$16,0)),"") | Q16: =IF($F16="","",IF($F16="D","NAO","SIM")) | R16: =IF(AND($M16="VERIFICADO",$Q16="SIM"),$P16,0) -> 0
... F201: =IFERROR(INDEX(Catalogo!$C$2:$C$29,MATCH($E201,Catalogo!$B$2:$B$29,0)),"") | G201: =IFERROR(INDEX(Catalogo!$D$2:$D$29,MATCH($E201,Catalogo!$B$2:$B$29,0)),"") | H201: =IFERROR(INDEX(Catalogo!$E$2:$E$29,MATCH($E201,Catalogo!$B$2:$B$29,0)),"") | I201: =IFERROR(INDEX(Parametros!$C$13:$C$16,MATCH($F201,Parametros!$B$13:$B$16,0)),"") | J201: =IFERROR(INDEX(Parametros!$E$13:$E$16,MATCH($F201,Parametros!$B$13:$B$16,0)),"") | L201: =IF(OR($K201="",$J201="",$J201=0),"",$K201+$J201) | P201: =IFERROR(INDEX(Parametros!$D$13:$D$16,MATCH($F201,Parametros!$B$13:$B$16,0)),"") | Q201: =IF($F201="","",IF($F201="D","NAO","SIM")) | R201: =IF(AND($M201="VERIFICADO",$Q201="SIM"),$P201,0) -> 0

Sheet Casos
A1: Caso ID | B1: Cliente | C1: Tipo | D1: Data entrada | E1: Itens | F1: A | G1: B | H1: C | I1: D | J1: Diagnostico | K1: Execucao | L1: Exito realizado | M1: Monitor./mes | N1: Receita do caso | O1: Exito realizado % | P1: Exito esperado %
A2: C001 | B2: Exemplo - Joao Silva | C2: PF | D2: 2026-08-05 | E2: =IF($A2="","",COUNTIFS(Triagem!$B:$B,$A2)) -> 3 | F2: =IF($A2="","",COUNTIFS(Triagem!$B:$B,$A2,Triagem!$F:$F,"A")) -> 1 | G2: =IF($A2="","",COUNTIFS(Triagem!$B:$B,$A2,Triagem!$F:$F,"B")) -> 1 | H2: =IF($A2="","",COUNTIFS(Triagem!$B:$B,$A2,Triagem!$F:$F,"C")) -> 0 | I2: =IF($A2="","",COUNTIFS(Triagem!$B:$B,$A2,Triagem!$F:$F,"D")) -> 1 | J2: =IF($A2="","",Parametros!$C$6) -> 197 | K2: =IF($A2="","",$G2*Parametros!$C$7) -> 300 | L2: =IF($A2="","",SUMIFS(Triagem!$R:$R,Triagem!$B:$B,$A2)) -> 650 | M2: =IF($A2="","",IF($C2="PJ",Parametros!$C$9,Parametros!$C$8)) -> 79 | N2: =IF($A2="","",$J2+$K2+$L2) -> 1147 | O2: =IF($A2="","",IFERROR(COUNTIFS(Triagem!$B:$B,$A2,Triagem!$M:$M,"VERIFICADO")/COUNTIFS(Triagem!$B:$B,$A2,Triagem!$Q:$Q,"SIM"),"")) -> 0.5 | P2: =IF($A2="","",IFERROR(SUMIFS(Triagem!$I:$I,Triagem!$B:$B,$A2,Triagem!$Q:$Q,"SIM")/COUNTIFS(Triagem!$B:$B,$A2,Triagem!$Q:$Q,"SIM"),"")) -> 0.7375
E3: =IF($A3="","",COUNTIFS(Triagem!$B:$B,$A3)) | F3: =IF($A3="","",COUNTIFS(Triagem!$B:$B,$A3,Triagem!$F:$F,"A")) | G3: =IF($A3="","",COUNTIFS(Triagem!$B:$B,$A3,Triagem!$F:$F,"B")) | H3: =IF($A3="","",COUNTIFS(Triagem!$B:$B,$A3,Triagem!$F:$F,"C")) | I3: =IF($A3="","",COUNTIFS(Triagem!$B:$B,$A3,Triagem!$F:$F,"D")) | J3: =IF($A3="","",Parametros!$C$6) | K3: =IF($A3="","",$G3*Parametros!$C$7) | L3: =IF($A3="","",SUMIFS(Triagem!$R:$R,Triagem!$B:$B,$A3)) | M3: =IF($A3="","",IF($C3="PJ",Parametros!$C$9,Parametros!$C$8)) | N3: =IF($A3="","",$J3+$K3+$L3) | O3: =IF($A3="","",IFERROR(COUNTIFS(Triagem!$B:$B,$A3,Triagem!$M:$M,"VERIFICADO")/COUNTIFS(Triagem!$B:$B,$A3,Triagem!$Q:$Q,"SIM"),"")) | P3: =IF($A3="","",IFERROR(SUMIFS(Triagem!$I:$I,Triagem!$B:$B,$A3,Triagem!$Q:$Q,"SIM")/COUNTIFS(Triagem!$B:$B,$A3,Triagem!$Q:$Q,"SIM"),""))
E4: =IF($A4="","",COUNTIFS(Triagem!$B:$B,$A4)) | F4: =IF($A4="","",COUNTIFS(Triagem!$B:$B,$A4,Triagem!$F:$F,"A")) | G4: =IF($A4="","",COUNTIFS(Triagem!$B:$B,$A4,Triagem!$F:$F,"B")) | H4: =IF($A4="","",COUNTIFS(Triagem!$B:$B,$A4,Triagem!$F:$F,"C")) | I4: =IF($A4="","",COUNTIFS(Triagem!$B:$B,$A4,Triagem!$F:$F,"D")) | J4: =IF($A4="","",Parametros!$C$6) | K4: =IF($A4="","",$G4*Parametros!$C$7) | L4: =IF($A4="","",SUMIFS(Triagem!$R:$R,Triagem!$B:$B,$A4)) | M4: =IF($A4="","",IF($C4="PJ",Parametros!$C$9,Parametros!$C$8)) | N4: =IF($A4="","",$J4+$K4+$L4) | O4: =IF($A4="","",IFERROR(COUNTIFS(Triagem!$B:$B,$A4,Triagem!$M:$M,"VERIFICADO")/COUNTIFS(Triagem!$B:$B,$A4,Triagem!$Q:$Q,"SIM"),"")) | P4: =IF($A4="","",IFERROR(SUMIFS(Triagem!$I:$I,Triagem!$B:$B,$A4,Triagem!$Q:$Q,"SIM")/COUNTIFS(Triagem!$B:$B,$A4,Triagem!$Q:$Q,"SIM"),""))
E5: =IF($A5="","",COUNTIFS(Triagem!$B:$B,$A5)) | F5: =IF($A5="","",COUNTIFS(Triagem!$B:$B,$A5,Triagem!$F:$F,"A")) | G5: =IF($A5="","",COUNTIFS(Triagem!$B:$B,$A5,Triagem!$F:$F,"B")) | H5: =IF($A5="","",COUNTIFS(Triagem!$B:$B,$A5,Triagem!$F:$F,"C")) | I5: =IF($A5="","",COUNTIFS(Triagem!$B:$B,$A5,Triagem!$F:$F,"D")) | J5: =IF($A5="","",Parametros!$C$6) | K5: =IF($A5="","",$G5*Parametros!$C$7) | L5: =IF($A5="","",SUMIFS(Triagem!$R:$R,Triagem!$B:$B,$A5)) | M5: =IF($A5="","",IF($C5="PJ",Parametros!$C$9,Parametros!$C$8)) | N5: =IF($A5="","",$J5+$K5+$L5) | O5: =IF($A5="","",IFERROR(COUNTIFS(Triagem!$B:$B,$A5,Triagem!$M:$M,"VERIFICADO")/COUNTIFS(Triagem!$B:$B,$A5,Triagem!$Q:$Q,"SIM"),"")) | P5: =IF($A5="","",IFERROR(SUMIFS(Triagem!$I:$I,Triagem!$B:$B,$A5,Triagem!$Q:$Q,"SIM")/COUNTIFS(Triagem!$B:$B,$A5,Triagem!$Q:$Q,"SIM"),""))
E6: =IF($A6="","",COUNTIFS(Triagem!$B:$B,$A6)) | F6: =IF($A6="","",COUNTIFS(Triagem!$B:$B,$A6,Triagem!$F:$F,"A")) | G6: =IF($A6="","",COUNTIFS(Triagem!$B:$B,$A6,Triagem!$F:$F,"B")) | H6: =IF($A6="","",COUNTIFS(Triagem!$B:$B,$A6,Triagem!$F:$F,"C")) | I6: =IF($A6="","",COUNTIFS(Triagem!$B:$B,$A6,Triagem!$F:$F,"D")) | J6: =IF($A6="","",Parametros!$C$6) | K6: =IF($A6="","",$G6*Parametros!$C$7) | L6: =IF($A6="","",SUMIFS(Triagem!$R:$R,Triagem!$B:$B,$A6)) | M6: =IF($A6="","",IF($C6="PJ",Parametros!$C$9,Parametros!$C$8)) | N6: =IF($A6="","",$J6+$K6+$L6) | O6: =IF($A6="","",IFERROR(COUNTIFS(Triagem!$B:$B,$A6,Triagem!$M:$M,"VERIFICADO")/COUNTIFS(Triagem!$B:$B,$A6,Triagem!$Q:$Q,"SIM"),"")) | P6: =IF($A6="","",IFERROR(SUMIFS(Triagem!$I:$I,Triagem!$B:$B,$A6,Triagem!$Q:$Q,"SIM")/COUNTIFS(Triagem!$B:$B,$A6,Triagem!$Q:$Q,"SIM"),""))
E7: =IF($A7="","",COUNTIFS(Triagem!$B:$B,$A7)) | F7: =IF($A7="","",COUNTIFS(Triagem!$B:$B,$A7,Triagem!$F:$F,"A")) | G7: =IF($A7="","",COUNTIFS(Triagem!$B:$B,$A7,Triagem!$F:$F,"B")) | H7: =IF($A7="","",COUNTIFS(Triagem!$B:$B,$A7,Triagem!$F:$F,"C")) | I7: =IF($A7="","",COUNTIFS(Triagem!$B:$B,$A7,Triagem!$F:$F,"D")) | J7: =IF($A7="","",Parametros!$C$6) | K7: =IF($A7="","",$G7*Parametros!$C$7) | L7: =IF($A7="","",SUMIFS(Triagem!$R:$R,Triagem!$B:$B,$A7)) | M7: =IF($A7="","",IF($C7="PJ",Parametros!$C$9,Parametros!$C$8)) | N7: =IF($A7="","",$J7+$K7+$L7) | O7: =IF($A7="","",IFERROR(COUNTIFS(Triagem!$B:$B,$A7,Triagem!$M:$M,"VERIFICADO")/COUNTIFS(Triagem!$B:$B,$A7,Triagem!$Q:$Q,"SIM"),"")) | P7: =IF($A7="","",IFERROR(SUMIFS(Triagem!$I:$I,Triagem!$B:$B,$A7,Triagem!$Q:$Q,"SIM")/COUNTIFS(Triagem!$B:$B,$A7,Triagem!$Q:$Q,"SIM"),""))
E8: =IF($A8="","",COUNTIFS(Triagem!$B:$B,$A8)) | F8: =IF($A8="","",COUNTIFS(Triagem!$B:$B,$A8,Triagem!$F:$F,"A")) | G8: =IF($A8="","",COUNTIFS(Triagem!$B:$B,$A8,Triagem!$F:$F,"B")) | H8: =IF($A8="","",COUNTIFS(Triagem!$B:$B,$A8,Triagem!$F:$F,"C")) | I8: =IF($A8="","",COUNTIFS(Triagem!$B:$B,$A8,Triagem!$F:$F,"D")) | J8: =IF($A8="","",Parametros!$C$6) | K8: =IF($A8="","",$G8*Parametros!$C$7) | L8: =IF($A8="","",SUMIFS(Triagem!$R:$R,Triagem!$B:$B,$A8)) | M8: =IF($A8="","",IF($C8="PJ",Parametros!$C$9,Parametros!$C$8)) | N8: =IF($A8="","",$J8+$K8+$L8) | O8: =IF($A8="","",IFERROR(COUNTIFS(Triagem!$B:$B,$A8,Triagem!$M:$M,"VERIFICADO")/COUNTIFS(Triagem!$B:$B,$A8,Triagem!$Q:$Q,"SIM"),"")) | P8: =IF($A8="","",IFERROR(SUMIFS(Triagem!$I:$I,Triagem!$B:$B,$A8,Triagem!$Q:$Q,"SIM")/COUNTIFS(Triagem!$B:$B,$A8,Triagem!$Q:$Q,"SIM"),""))
E9: =IF($A9="","",COUNTIFS(Triagem!$B:$B,$A9)) | F9: =IF($A9="","",COUNTIFS(Triagem!$B:$B,$A9,Triagem!$F:$F,"A")) | G9: =IF($A9="","",COUNTIFS(Triagem!$B:$B,$A9,Triagem!$F:$F,"B")) | H9: =IF($A9="","",COUNTIFS(Triagem!$B:$B,$A9,Triagem!$F:$F,"C")) | I9: =IF($A9="","",COUNTIFS(Triagem!$B:$B,$A9,Triagem!$F:$F,"D")) | J9: =IF($A9="","",Parametros!$C$6) | K9: =IF($A9="","",$G9*Parametros!$C$7) | L9: =IF($A9="","",SUMIFS(Triagem!$R:$R,Triagem!$B:$B,$A9)) | M9: =IF($A9="","",IF($C9="PJ",Parametros!$C$9,Parametros!$C$8)) | N9: =IF($A9="","",$J9+$K9+$L9) | O9: =IF($A9="","",IFERROR(COUNTIFS(Triagem!$B:$B,$A9,Triagem!$M:$M,"VERIFICADO")/COUNTIFS(Triagem!$B:$B,$A9,Triagem!$Q:$Q,"SIM"),"")) | P9: =IF($A9="","",IFERROR(SUMIFS(Triagem!$I:$I,Triagem!$B:$B,$A9,Triagem!$Q:$Q,"SIM")/COUNTIFS(Triagem!$B:$B,$A9,Triagem!$Q:$Q,"SIM"),""))
E10: =IF($A10="","",COUNTIFS(Triagem!$B:$B,$A10)) | F10: =IF($A10="","",COUNTIFS(Triagem!$B:$B,$A10,Triagem!$F:$F,"A")) | G10: =IF($A10="","",COUNTIFS(Triagem!$B:$B,$A10,Triagem!$F:$F,"B")) | H10: =IF($A10="","",COUNTIFS(Triagem!$B:$B,$A10,Triagem!$F:$F,"C")) | I10: =IF($A10="","",COUNTIFS(Triagem!$B:$B,$A10,Triagem!$F:$F,"D")) | J10: =IF($A10="","",Parametros!$C$6) | K10: =IF($A10="","",$G10*Parametros!$C$7) | L10: =IF($A10="","",SUMIFS(Triagem!$R:$R,Triagem!$B:$B,$A10)) | M10: =IF($A10="","",IF($C10="PJ",Parametros!$C$9,Parametros!$C$8)) | N10: =IF($A10="","",$J10+$K10+$L10) | O10: =IF($A10="","",IFERROR(COUNTIFS(Triagem!$B:$B,$A10,Triagem!$M:$M,"VERIFICADO")/COUNTIFS(Triagem!$B:$B,$A10,Triagem!$Q:$Q,"SIM"),"")) | P10: =IF($A10="","",IFERROR(SUMIFS(Triagem!$I:$I,Triagem!$B:$B,$A10,Triagem!$Q:$Q,"SIM")/COUNTIFS(Triagem!$B:$B,$A10,Triagem!$Q:$Q,"SIM"),""))
E11: =IF($A11="","",COUNTIFS(Triagem!$B:$B,$A11)) | F11: =IF($A11="","",COUNTIFS(Triagem!$B:$B,$A11,Triagem!$F:$F,"A")) | G11: =IF($A11="","",COUNTIFS(Triagem!$B:$B,$A11,Triagem!$F:$F,"B")) | H11: =IF($A11="","",COUNTIFS(Triagem!$B:$B,$A11,Triagem!$F:$F,"C")) | I11: =IF($A11="","",COUNTIFS(Triagem!$B:$B,$A11,Triagem!$F:$F,"D")) | J11: =IF($A11="","",Parametros!$C$6) | K11: =IF($A11="","",$G11*Parametros!$C$7) | L11: =IF($A11="","",SUMIFS(Triagem!$R:$R,Triagem!$B:$B,$A11)) | M11: =IF($A11="","",IF($C11="PJ",Parametros!$C$9,Parametros!$C$8)) | N11: =IF($A11="","",$J11+$K11+$L11) | O11: =IF($A11="","",IFERROR(COUNTIFS(Triagem!$B:$B,$A11,Triagem!$M:$M,"VERIFICADO")/COUNTIFS(Triagem!$B:$B,$A11,Triagem!$Q:$Q,"SIM"),"")) | P11: =IF($A11="","",IFERROR(SUMIFS(Triagem!$I:$I,Triagem!$B:$B,$A11,Triagem!$Q:$Q,"SIM")/COUNTIFS(Triagem!$B:$B,$A11,Triagem!$Q:$Q,"SIM"),""))
E12: =IF($A12="","",COUNTIFS(Triagem!$B:$B,$A12)) | F12: =IF($A12="","",COUNTIFS(Triagem!$B:$B,$A12,Triagem!$F:$F,"A")) | G12: =IF($A12="","",COUNTIFS(Triagem!$B:$B,$A12,Triagem!$F:$F,"B")) | H12: =IF($A12="","",COUNTIFS(Triagem!$B:$B,$A12,Triagem!$F:$F,"C")) | I12: =IF($A12="","",COUNTIFS(Triagem!$B:$B,$A12,Triagem!$F:$F,"D")) | J12: =IF($A12="","",Parametros!$C$6) | K12: =IF($A12="","",$G12*Parametros!$C$7) | L12: =IF($A12="","",SUMIFS(Triagem!$R:$R,Triagem!$B:$B,$A12)) | M12: =IF($A12="","",IF($C12="PJ",Parametros!$C$9,Parametros!$C$8)) | N12: =IF($A12="","",$J12+$K12+$L12) | O12: =IF($A12="","",IFERROR(COUNTIFS(Triagem!$B:$B,$A12,Triagem!$M:$M,"VERIFICADO")/COUNTIFS(Triagem!$B:$B,$A12,Triagem!$Q:$Q,"SIM"),"")) | P12: =IF($A12="","",IFERROR(SUMIFS(Triagem!$I:$I,Triagem!$B:$B,$A12,Triagem!$Q:$Q,"SIM")/COUNTIFS(Triagem!$B:$B,$A12,Triagem!$Q:$Q,"SIM"),""))
E13: =IF($A13="","",COUNTIFS(Triagem!$B:$B,$A13)) | F13: =IF($A13="","",COUNTIFS(Triagem!$B:$B,$A13,Triagem!$F:$F,"A")) | G13: =IF($A13="","",COUNTIFS(Triagem!$B:$B,$A13,Triagem!$F:$F,"B")) | H13: =IF($A13="","",COUNTIFS(Triagem!$B:$B,$A13,Triagem!$F:$F,"C")) | I13: =IF($A13="","",COUNTIFS(Triagem!$B:$B,$A13,Triagem!$F:$F,"D")) | J13: =IF($A13="","",Parametros!$C$6) | K13: =IF($A13="","",$G13*Parametros!$C$7) | L13: =IF($A13="","",SUMIFS(Triagem!$R:$R,Triagem!$B:$B,$A13)) | M13: =IF($A13="","",IF($C13="PJ",Parametros!$C$9,Parametros!$C$8)) | N13: =IF($A13="","",$J13+$K13+$L13) | O13: =IF($A13="","",IFERROR(COUNTIFS(Triagem!$B:$B,$A13,Triagem!$M:$M,"VERIFICADO")/COUNTIFS(Triagem!$B:$B,$A13,Triagem!$Q:$Q,"SIM"),"")) | P13: =IF($A13="","",IFERROR(SUMIFS(Triagem!$I:$I,Triagem!$B:$B,$A13,Triagem!$Q:$Q,"SIM")/COUNTIFS(Triagem!$B:$B,$A13,Triagem!$Q:$Q,"SIM"),""))
E14: =IF($A14="","",COUNTIFS(Triagem!$B:$B,$A14)) | F14: =IF($A14="","",COUNTIFS(Triagem!$B:$B,$A14,Triagem!$F:$F,"A")) | G14: =IF($A14="","",COUNTIFS(Triagem!$B:$B,$A14,Triagem!$F:$F,"B")) | H14: =IF($A14="","",COUNTIFS(Triagem!$B:$B,$A14,Triagem!$F:$F,"C")) | I14: =IF($A14="","",COUNTIFS(Triagem!$B:$B,$A14,Triagem!$F:$F,"D")) | J14: =IF($A14="","",Parametros!$C$6) | K14: =IF($A14="","",$G14*Parametros!$C$7) | L14: =IF($A14="","",SUMIFS(Triagem!$R:$R,Triagem!$B:$B,$A14)) | M14: =IF($A14="","",IF($C14="PJ",Parametros!$C$9,Parametros!$C$8)) | N14: =IF($A14="","",$J14+$K14+$L14) | O14: =IF($A14="","",IFERROR(COUNTIFS(Triagem!$B:$B,$A14,Triagem!$M:$M,"VERIFICADO")/COUNTIFS(Triagem!$B:$B,$A14,Triagem!$Q:$Q,"SIM"),"")) | P14: =IF($A14="","",IFERROR(SUMIFS(Triagem!$I:$I,Triagem!$B:$B,$A14,Triagem!$Q:$Q,"SIM")/COUNTIFS(Triagem!$B:$B,$A14,Triagem!$Q:$Q,"SIM"),""))
... E61: =IF($A61="","",COUNTIFS(Triagem!$B:$B,$A61)) | F61: =IF($A61="","",COUNTIFS(Triagem!$B:$B,$A61,Triagem!$F:$F,"A")) | G61: =IF($A61="","",COUNTIFS(Triagem!$B:$B,$A61,Triagem!$F:$F,"B")) | H61: =IF($A61="","",COUNTIFS(Triagem!$B:$B,$A61,Triagem!$F:$F,"C")) | I61: =IF($A61="","",COUNTIFS(Triagem!$B:$B,$A61,Triagem!$F:$F,"D")) | J61: =IF($A61="","",Parametros!$C$6) | K61: =IF($A61="","",$G61*Parametros!$C$7) | L61: =IF($A61="","",SUMIFS(Triagem!$R:$R,Triagem!$B:$B,$A61)) | M61: =IF($A61="","",IF($C61="PJ",Parametros!$C$9,Parametros!$C$8)) | N61: =IF($A61="","",$J61+$K61+$L61) | O61: =IF($A61="","",IFERROR(COUNTIFS(Triagem!$B:$B,$A61,Triagem!$M:$M,"VERIFICADO")/COUNTIFS(Triagem!$B:$B,$A61,Triagem!$Q:$Q,"SIM"),"")) | P61: =IF($A61="","",IFERROR(SUMIFS(Triagem!$I:$I,Triagem!$B:$B,$A61,Triagem!$Q:$Q,"SIM")/COUNTIFS(Triagem!$B:$B,$A61,Triagem!$Q:$Q,"SIM"),""))

Sheet Painel
B1: PAINEL DE INDICADORES
B2: Somente leitura. Todos os valores derivam das abas Triagem e Casos.
B4: OPERACIONAL
B5: Itens cadastrados | C5: =COUNTA(Triagem!$A$2:$A$201) -> 3 | E5: Uma linha por URL.
B6: Itens faturaveis (faixas A, B, C) | C6: =COUNTIF(Triagem!$Q$2:$Q$201,"SIM") -> 2 | E6: Faixa D nunca entra.
B7: Itens recusados (faixa D) | C7: =COUNTIF(Triagem!$Q$2:$Q$201,"NAO") -> 1 | E7: Volume alto aqui indica falha na qualificacao (Fase 0).
B8: Itens verificados | C8: =COUNTIF(Triagem!$M$2:$M$201,"VERIFICADO") -> 1 | E8: Unico status que autoriza faturamento de exito.
B9: Itens indeferidos | C9: =COUNTIF(Triagem!$M$2:$M$201,"INDEFERIDO") -> 0 | E9: Decidir: recurso, escalonamento juridico ou encerramento.
B10: Itens em aberto | C10: =COUNTIF(Triagem!$M$2:$M$201,"TRIADO")+COUNTIF(Triagem!$M$2:$M$201,"PROTOCOLADO")+COUNTIF(Triagem!$M$2:$M$201,"EM ANALISE") -> 1 | E10: Carga de trabalho atual.
B11: Itens fora do prazo | C11: =SUMPRODUCT((Triagem!$L$2:$L$201<>"")*(Triagem!$L$2:$L$201<TODAY())*(Triagem!$M$2:$M$201<>"VERIFICADO")*(Triagem!$M$2:$M$201<>"ENCERRADO")*(Triagem!$M$2:$M$201<>"RECUSADO")) -> 0 | E11: Violacao de SLA. Meta: zero.
B13: CALIBRACAO DA MATRIZ
B14: Exito real global | C14: =IFERROR(COUNTIF(Triagem!$M$2:$M$201,"VERIFICADO")/COUNTIF(Triagem!$Q$2:$Q$201,"SIM"),"") -> 0.5 | E14: Comparar com a linha abaixo.
B15: Exito esperado global | C15: =IFERROR(SUMIFS(Triagem!$I$2:$I$201,Triagem!$Q$2:$Q$201,"SIM")/COUNTIF(Triagem!$Q$2:$Q$201,"SIM"),"") -> 0.7375 | E15: Media ponderada das faixas atribuidas.
B16: Desvio (real - esperado) | C16: =IFERROR($C$14-$C$15,"") -> -0.2375 | E16: Acima de 20% em modulo: reclassificar tipos no Catalogo.
B17: Exito real - Faixa A | C17: =IFERROR(COUNTIFS(Triagem!$F$2:$F$201,"A",Triagem!$M$2:$M$201,"VERIFICADO")/COUNTIF(Triagem!$F$2:$F$201,"A"),"") -> 1 | E17: Esperado: 87,5%
B18: Exito real - Faixa B | C18: =IFERROR(COUNTIFS(Triagem!$F$2:$F$201,"B",Triagem!$M$2:$M$201,"VERIFICADO")/COUNTIF(Triagem!$F$2:$F$201,"B"),"") -> 0 | E18: Esperado: 60,0%
B19: Exito real - Faixa C | C19: =IFERROR(COUNTIFS(Triagem!$F$2:$F$201,"C",Triagem!$M$2:$M$201,"VERIFICADO")/COUNTIF(Triagem!$F$2:$F$201,"C"),"") | E19: Esperado: 27,5%
B21: FINANCEIRO
B22: Casos ativos | C22: =COUNTA(Casos!$A$2:$A$61) -> 1
B23: Receita de diagnostico | C23: =SUMIF(Casos!$A$2:$A$61,"<>",Casos!$J$2:$J$61) -> 197 | E23: Base previsivel. Cobrada sempre.
B24: Receita de execucao | C24: =SUM(Casos!$K$2:$K$61) -> 300 | E24: Somente itens de Faixa B.
B25: Receita de exito realizada | C25: =SUM(Triagem!$R$2:$R$201) -> 650 | E25: So conta apos verificacao.
B26: Receita total realizada | C26: =$C$23+$C$24+$C$25 -> 1147 | E26: Evento unico. Nao compoe.
B27: Monitoramento contratado (MRR) | C27: =SUM(Casos!$M$2:$M$61) -> 79 | E27: A metrica que define a sustentabilidade do negocio.
B28: Itens medios por caso | C28: =IFERROR($C$5/$C$22,"") -> 3 | E28: Casos com muitos itens A e B sao os rentaveis.
B29: Receita media por caso | C29: =IFERROR($C$26/$C$22,"") -> 1147
B31: Regra de calibracao: a cada 20 casos encerrados, comparar exito real e esperado por faixa. Desvio acima de 20% exige reclassificar o tipo de conteudo na aba Catalogo e atualizar o README do repositorio.
